pihub/__init__.py
pihub-0.0.0.dist-info/METADATA
pihub-0.0.0.dist-info/WHEEL
pihub-0.0.0.dist-info/top_level.txt
pihub-0.0.0.dist-info/RECORD
