Metadata-Version: 2.4
Name: pihub
Version: 0.0.0
Summary: Coming soon, under development.
Author-email: Will Brown <williambrown97@gmail.com>
License: MIT
Project-URL: Homepage, https://pihub.ai
Requires-Python: >=3.11
